mc_aircraft_campaign/__init__.py
mc_aircraft_campaign/aircraft_campaign.py
mc_aircraft_campaign/images/bg1.jpg
mc_aircraft_campaign/images/bg2.jpg
mc_aircraft_campaign/images/bg3.jpg
mc_aircraft_campaign/images/bg4.jpg
mc_aircraft_campaign/images/bg5.jpg
mc_aircraft_campaign/images/boom-1.png
mc_aircraft_campaign/images/boom-2.png
mc_aircraft_campaign/images/boom-3.png
mc_aircraft_campaign/images/boom-4.png
mc_aircraft_campaign/images/boom-5.png
mc_aircraft_campaign/images/boom-6.png
mc_aircraft_campaign/images/boom-7.png
mc_aircraft_campaign/images/bullet-1.png
mc_aircraft_campaign/images/bullet-2.png
mc_aircraft_campaign/images/e1.png
mc_aircraft_campaign/images/e2.png
mc_aircraft_campaign/images/p1.png
mc_aircraft_campaign/music/bgm.mp3
mc_aircraft_campaign/sounds/boom.wav
mc_aircraft_campaign-0.4.dist-info/LICENSE
mc_aircraft_campaign-0.4.dist-info/METADATA
mc_aircraft_campaign-0.4.dist-info/WHEEL
mc_aircraft_campaign-0.4.dist-info/entry_points.txt
mc_aircraft_campaign-0.4.dist-info/top_level.txt
mc_aircraft_campaign-0.4.dist-info/RECORD
