Metadata-Version: 2.1
Name: mc-aircraft-campaign
Version: 0.4
Summary: aircraft_campaign
Home-page: UNKNOWN
Author: xuetianyin
Author-email: zuiwo9@outlook.com
License: UNKNOWN
Platform: UNKNOWN
Classifier: Programming Language :: Python :: 3
Classifier: License :: OSI Approved :: MIT License
Classifier: Operating System :: OS Independent
Requires-Dist: mc-pgzrun (>=0.9)
